amjed_simple_regression-1.0.0.dist-info/licenses/LICENSE.txt
simple_regression/__init__.py
simple_regression/regression.py
amjed_simple_regression-1.0.0.dist-info/METADATA
amjed_simple_regression-1.0.0.dist-info/WHEEL
amjed_simple_regression-1.0.0.dist-info/top_level.txt
amjed_simple_regression-1.0.0.dist-info/RECORD
