Metadata-Version: 2.4
Name: amjed_simple_regression
Version: 1.0.0
Summary: Simple Linear Regression from scratch
Author: your name
License-File: LICENSE.txt
Dynamic: author
Dynamic: license-file
Dynamic: summary
